nicegui_react/__init__.py
nicegui_react/react.py
nicegui_react-0.1.7.dist-info/LICENSE
nicegui_react-0.1.7.dist-info/METADATA
nicegui_react-0.1.7.dist-info/WHEEL
nicegui_react-0.1.7.dist-info/top_level.txt
nicegui_react-0.1.7.dist-info/RECORD
